hatch_bgd/__about__.py
hatch_bgd/__init__.py
hatch_bgd/hooks.py
hatch_bgd/version_source.py
hatch_bgd-0.0.1.dist-info/METADATA
hatch_bgd-0.0.1.dist-info/WHEEL
hatch_bgd-0.0.1.dist-info/entry_points.txt
hatch_bgd-0.0.1.dist-info/RECORD
