Metadata-Version: 2.4
Name: hatch-bgd
Version: 0.0.1
Summary: ​base version, ​latest Git commit ID, and ​latest update date.
Project-URL: Source, https://github.com/townwish4git/hatch-bgd
Author-email: TownWish <townwish2023@outlook.com>
License: MIT
Keywords: git,hatch,plugin,version
Classifier: Development Status :: 4 - Beta
Classifier: Programming Language :: Python
Classifier: Programming Language :: Python :: 3.8
Classifier: Programming Language :: Python :: 3.9
Classifier: Programming Language :: Python :: 3.10
Classifier: Programming Language :: Python :: 3.11
Classifier: Programming Language :: Python :: 3.12
Classifier: Programming Language :: Python :: Implementation :: CPython
Classifier: Programming Language :: Python :: Implementation :: PyPy
Requires-Python: >=3.8
Requires-Dist: hatchling>=1.1.0
